superbig/__init__.py
superbig/base.py
superbig/chunker/__init__.py
superbig/chunker/naive.py
superbig/chunker/paragraph.py
superbig/collector/__init__.py
superbig/collector/chroma.py
superbig/collector/custom.py
superbig/embedder/__init__.py
superbig/embedder/sentence_transformer.py
superbig/focuser/__init__.py
superbig/focuser/basic.py
superbig/injector/__init__.py
superbig/injector/generic.py
superbig/metadata/__init__.py
superbig/metadata/builder.py
superbig/prepared_prompt/__init__.py
superbig/prepared_prompt/alpaca.py
superbig/prepared_prompt/generic.py
superbig/provider/__init__.py
superbig/provider/provider.py
superbig/searcher/__init__.py
superbig/searcher/asymmetric_similarity.py
superbig/searcher/cosine_similarity.py
superbig/source/__init__.py
superbig/source/file_source.py
superbig/source/source_builder.py
superbig/source/source_selector.py
superbig/source/text_source.py
superbig/source/url_source.py
superbig-0.1.0.dist-info/METADATA
superbig-0.1.0.dist-info/WHEEL
superbig-0.1.0.dist-info/licenses/LICENSE
superbig-0.1.0.dist-info/RECORD
