Metadata-Version: 2.1
Name: superbig
Version: 0.1.0
Summary: A small example package
Project-URL: Homepage, https://github.com/kaiokendev/superbig
Project-URL: Bug Tracker, https://github.com/kaiokendev/superbig/issues
Author-email: Kaiokendev <129691954+kaiokendev@users.noreply.github.com>
License-File: LICENSE
Classifier: License :: OSI Approved :: MIT License
Classifier: Operating System :: OS Independent
Classifier: Programming Language :: Python :: 3
Requires-Python: >=3.10
